{
    "category": "plugins",
    "display": "Add business days",
    "fields": {
        "AAD": {
            "caption": "start_date",
            "editor": "DynamicValue",
            "name": "start_date",
            "rank": 0,
            "value": "date"
        },
        "AAE": {
            "caption": "add_days",
            "editor": "DynamicValue",
            "name": "add_days",
            "rank": 1,
            "value": "number"
        }
    },
    "return_value": {
        "AAF": {
            "caption": "final_date",
            "name": "final_date",
            "rank": 0,
            "value": "date"
        }
    },
    "type": "server_side"
}